mathlib/__init__.py
mathlib/algebra.py
mathlib/arithmetic.py
mathlib/complex_numbers.py
mathlib/logarithmic.py
mathlib/logrithmic.py
mathlib/matrix_operations.py
mathlib/power_roots.py
mathlib/random_utils.py
mathlib/statistics.py
mathlib/trigonometry.py
mathlib/utility.py
arunp77_mathlib-0.1.dist-info/LICENCE
arunp77_mathlib-0.1.dist-info/METADATA
arunp77_mathlib-0.1.dist-info/WHEEL
arunp77_mathlib-0.1.dist-info/top_level.txt
arunp77_mathlib-0.1.dist-info/RECORD
