Metadata-Version: 2.1
Name: arunp77-mathlib
Version: 0.1
Summary: A simple math library with basic operations
Home-page: https://github.com/arunp77/Data-engineering-tools/matlib
Author: Arun Kumar Pandey
Author-email: arunp77@gmail.com
License: MIT
Classifier: Programming Language :: Python :: 3
Classifier: License :: OSI Approved :: MIT License
Classifier: Operating System :: OS Independent
License-File: LICENCE
